{
  "id": "MADIPAKKAM-UNDERPASS",
  "name": {
    "en": "Madipakkam Underpass",
    "ta": "மாதிப்பாக்கம் நிலத்தடி சாலை"
  },
  "location": {
    "district": "Chennai",
    "city": "Chennai",
    "coordinates": {
      "latitude": 12.9667,
      "longitude": 80.1989
    }
  },
  "type": "Roads/Highways",
  "status": "Completed",
  "budget": {
    "crore": null,
    "notes": null
  },
  "timeline": {
    "startYear": 2021,
    "completionYear": 2024,
    "completionNotes": "Completed and operational"
  },
  "media": {
    "photoUrl": null,
    "photoCaption": null,
    "cmPhotoInitiation": null,
    "cmPhotoCompletion": null
  },
  "sources": [
    {
      "title": "DMK Achievements - Chennai Flyovers",
      "url": "https://www.dmk.in/en/achievements/"
    },
    {
      "title": "DTNext - Chennai Infrastructure",
      "url": "https://www.dtnext.in/news/chennai/"
    }
  ],
  "notes": null
}